whisper_gui/__init__.py
whisper_gui/form.ui
whisper_gui/mainwindow.py
whisper_gui/ui_form.py
whisper_gui-0.1.0.dist-info/METADATA
whisper_gui-0.1.0.dist-info/WHEEL
whisper_gui-0.1.0.dist-info/entry_points.txt
whisper_gui-0.1.0.dist-info/licenses/LICENSE
whisper_gui-0.1.0.dist-info/RECORD
