Metadata-Version: 2.4
Name: whisper-gui
Version: 0.1.0
Summary: A GUI application for Whisper speech recognition
Author-email: "Frank T. Bergmann" <frank.thomas.bergmann@gmail.com>
License-Expression: MIT
License-File: LICENSE
Requires-Python: >=3.8
Requires-Dist: pyside6>=6.0.0
